lingo24/__init__.py
lingo24/exceptions.py
lingo24/business_documents/__init__.py
lingo24/business_documents/auth.py
lingo24/business_documents/client.py
lingo24/business_documents/collections.py
lingo24/business_documents/domains.py
lingo24/business_documents/endpoints.py
lingo24/business_documents/files.py
lingo24/business_documents/jobs.py
lingo24/business_documents/locales.py
lingo24/business_documents/pricing.py
lingo24/business_documents/projects.py
lingo24/business_documents/services.py
lingo24-1.1.0.dist-info/LICENSE
lingo24-1.1.0.dist-info/METADATA
lingo24-1.1.0.dist-info/WHEEL
lingo24-1.1.0.dist-info/top_level.txt
lingo24-1.1.0.dist-info/RECORD
